geo_poi_normalizer/__init__.py
geo_poi_normalizer/normalizer.py
geo_poi_normalizer/print_report.py
geo_poi_normalizer/examples/__init__.py
geo_poi_normalizer/examples/basic_usage.py
geo_poi_normalizer/examples/shapefile_usage.py
geo_poi_normalizer/examples/visualization_example.py
geo_poi_normalizer/tests/__init__.py
geo_poi_normalizer/tests/run_tests.py
geo_poi_normalizer/tests/test_normalizer.py
geo_poi_normalizer/tests/test_visualization.py
geo_poi_normalizer-0.1.0.dist-info/METADATA
geo_poi_normalizer-0.1.0.dist-info/WHEEL
geo_poi_normalizer-0.1.0.dist-info/top_level.txt
geo_poi_normalizer-0.1.0.dist-info/RECORD
