Metadata-Version: 2.4
Name: geo-poi-normalizer
Version: 0.1.0
Summary: 地理POI归一化处理库，采用投影转换+各向同性缩放方案
Home-page: https://github.com/yourusername/geo-poi-normalizer
Author: Tencent Cloud
Author-email: example@example.com
Keywords: gis,normalization,poi,geospatial,coordinates,projection,utm
Classifier: Programming Language :: Python :: 3
Classifier: License :: OSI Approved :: MIT License
Classifier: Operating System :: OS Independent
Classifier: Topic :: Scientific/Engineering :: GIS
Classifier: Intended Audience :: Developers
Classifier: Intended Audience :: Science/Research
Requires-Python: >=3.6
Requires-Dist: numpy>=1.18.0
Requires-Dist: pyproj>=2.6.0
Requires-Dist: pyshp>=2.1.0
Dynamic: author
Dynamic: author-email
Dynamic: classifier
Dynamic: description
Dynamic: description-content-type
Dynamic: home-page
Dynamic: keywords
Dynamic: requires-dist
Dynamic: requires-python
Dynamic: summary
